codevid/__init__.py
codevid/cli.py
codevid/config.py
codevid/pipeline.py
codevid/audio/__init__.py
codevid/audio/edge_tts.py
codevid/audio/factory.py
codevid/audio/kokoro_provider.py
codevid/audio/openai_tts.py
codevid/audio/tts.py
codevid/composer/__init__.py
codevid/composer/captions.py
codevid/composer/editor.py
codevid/composer/overlays.py
codevid/composer/templates.py
codevid/executor/__init__.py
codevid/executor/mouse_helper.py
codevid/executor/playwright.py
codevid/llm/__init__.py
codevid/llm/base.py
codevid/llm/factory.py
codevid/llm/prompts.py
codevid/llm/provider_anthropic.py
codevid/llm/provider_ollama.py
codevid/llm/provider_openai.py
codevid/llm/provider_simple.py
codevid/models/__init__.py
codevid/models/project.py
codevid/models/script.py
codevid/models/test_step.py
codevid/parsers/__init__.py
codevid/parsers/base.py
codevid/parsers/playwright.py
codevid/parsers/registry.py
codevid/recorder/__init__.py
codevid/recorder/screen.py
codevid-1.5.0.dist-info/METADATA
codevid-1.5.0.dist-info/WHEEL
codevid-1.5.0.dist-info/entry_points.txt
codevid-1.5.0.dist-info/licenses/LICENSE
codevid-1.5.0.dist-info/RECORD
