Metadata-Version: 2.4
Name: codevid
Version: 1.5.0
Summary: Generate video tutorials from automated tests using LLMs
Author: Mateusz Staniaszek
License: MIT
License-File: LICENSE
Keywords: automation,llm,playwright,testing,tutorial,video
Classifier: Development Status :: 3 - Alpha
Classifier: Environment :: Console
Classifier: Intended Audience :: Developers
Classifier: License :: OSI Approved :: MIT License
Classifier: Programming Language :: Python :: 3.11
Classifier: Programming Language :: Python :: 3.12
Classifier: Topic :: Multimedia :: Video
Classifier: Topic :: Software Development :: Testing
Requires-Python: >=3.11
Requires-Dist: anthropic>=0.18.0
Requires-Dist: edge-tts>=6.1.0
Requires-Dist: flask>=3.0.0
Requires-Dist: httpx>=0.25.0
Requires-Dist: moviepy>=2.2.1
Requires-Dist: mss>=9.0.0
Requires-Dist: mutagen>=1.47.0
Requires-Dist: openai>=1.0.0
Requires-Dist: playwright>=1.40.0
Requires-Dist: pydantic-settings>=2.0.0
Requires-Dist: pydantic>=2.0.0
Requires-Dist: pytest>=9.0.2
Requires-Dist: pyyaml>=6.0
Requires-Dist: rich>=13.0.0
Requires-Dist: typer>=0.9.0
Provides-Extra: dev
Requires-Dist: mypy>=1.0.0; extra == 'dev'
Requires-Dist: pytest-asyncio>=0.21.0; extra == 'dev'
Requires-Dist: pytest>=7.0.0; extra == 'dev'
Requires-Dist: ruff>=0.1.0; extra == 'dev'
